{
  "manifestVersion": "3.2",
  "proxies": [
    {
      "address": "0x0FD0d9aa44a05Ee158DDf6F01d7dcF503388781d",
      "txHash": "0xe363083a4dd6173493c5b980565bcab9ce8ad983b68e27a4af57ea0356205f90",
      "kind": "uups"
    },
    {
      "address": "0xb9d5B99d5D0fA04dD7eb2b0CD7753317C2ea1a84",
      "txHash": "0x36dc4fcd722eb1be999bf658b7ac0968f996a17a4e040673cdf493a903dd1ae2",
      "kind": "uups"
    },
    {
      "address": "0x61bCd1ED11fC03C958A847A6687b1875f5eAcaaf",
      "txHash": "0xf35dd26f2741b428b33828578966c07569ac39b517234792a01b6dc664cec728",
      "kind": "uups"
    },
    {
      "address": "0xcA6b9D59849EC880e82210e9cb8237E1d0cAA69e",
      "txHash": "0xe0be2899fc7fc099be4a0010b342494e760b656e612ffbc132a6122f3dc075fa",
      "kind": "uups"
    }
  ],
  "impls": {
    "0435da29931225bdcda20c672c19f492191227a80573595532eed1611473fa33": {
      "address": "0xAE38a794E839D045460839ABe288a8e5C28B0fc6",
      "txHash": "0xe16c145cb9066604563465a63c7f54e1b79eb48821696aa218b6fa1c15e92a4c",
      "layout": {
        "storage": [
          {
            "contract": "Initializable",
            "label": "_initialized",
            "type": "t_bool",
            "src": "@openzeppelin/contracts-upgradeable/proxy/utils/Initializable.sol:21"
          },
          {
            "contract": "Initializable",
            "label": "_initializing",
            "type": "t_bool",
            "src": "@openzeppelin/contracts-upgradeable/proxy/utils/Initializable.sol:26"
          },
          {
            "contract": "ContextUpgradeable",
            "label": "__gap",
            "type": "t_array(t_uint256)50_storage",
            "src": "@openzeppelin/contracts-upgradeable/utils/ContextUpgradeable.sol:30"
          },
          {
            "contract": "ERC165Upgradeable",
            "label": "__gap",
            "type": "t_array(t_uint256)50_storage",
            "src": "@openzeppelin/contracts-upgradeable/utils/introspection/ERC165Upgradeable.sol:35"
          },
          {
            "contract": "ERC1155Upgradeable",
            "label": "_balances",
            "type": "t_mapping(t_uint256,t_mapping(t_address,t_uint256))",
            "src": "@openzeppelin/contracts-upgradeable/token/ERC1155/ERC1155Upgradeable.sol:24"
          },
          {
            "contract": "ERC1155Upgradeable",
            "label": "_operatorApprovals",
            "type": "t_mapping(t_address,t_mapping(t_address,t_bool))",
            "src": "@openzeppelin/contracts-upgradeable/token/ERC1155/ERC1155Upgradeable.sol:27"
          },
          {
            "contract": "ERC1155Upgradeable",
            "label": "_uri",
            "type": "t_string_storage",
            "src": "@openzeppelin/contracts-upgradeable/token/ERC1155/ERC1155Upgradeable.sol:30"
          },
          {
            "contract": "ERC1155Upgradeable",
            "label": "__gap",
            "type": "t_array(t_uint256)47_storage",
            "src": "@openzeppelin/contracts-upgradeable/token/ERC1155/ERC1155Upgradeable.sol:458"
          },
          {
            "contract": "ERC1967UpgradeUpgradeable",
            "label": "__gap",
            "type": "t_array(t_uint256)50_storage",
            "src": "@openzeppelin/contracts-upgradeable/proxy/ERC1967/ERC1967UpgradeUpgradeable.sol:214"
          },
          {
            "contract": "UUPSUpgradeable",
            "label": "__gap",
            "type": "t_array(t_uint256)50_storage",
            "src": "@openzeppelin/contracts-upgradeable/proxy/utils/UUPSUpgradeable.sol:64"
          },
          {
            "contract": "OwnableSlice",
            "label": "_slice",
            "type": "t_address",
            "src": "contracts/utils/ownableSlice.sol:8"
          },
          {
            "contract": "OwnableSlice",
            "label": "_owner",
            "type": "t_address",
            "src": "contracts/utils/ownableSlice.sol:9"
          },
          {
            "contract": "OwnableSlice",
            "label": "__gap",
            "type": "t_array(t_uint256)49_storage",
            "src": "contracts/utils/ownableSlice.sol:58"
          },
          {
            "contract": "PausableUpgradeable",
            "label": "_paused",
            "type": "t_bool",
            "src": "@openzeppelin/contracts-upgradeable/security/PausableUpgradeable.sol:28"
          },
          {
            "contract": "PausableUpgradeable",
            "label": "__gap",
            "type": "t_array(t_uint256)49_storage",
            "src": "@openzeppelin/contracts-upgradeable/security/PausableUpgradeable.sol:96"
          },
          {
            "contract": "ReentrancyGuardUpgradeable",
            "label": "_status",
            "type": "t_uint256",
            "src": "@openzeppelin/contracts-upgradeable/security/ReentrancyGuardUpgradeable.sol:37"
          },
          {
            "contract": "ReentrancyGuardUpgradeable",
            "label": "__gap",
            "type": "t_array(t_uint256)49_storage",
            "src": "@openzeppelin/contracts-upgradeable/security/ReentrancyGuardUpgradeable.sol:67"
          },
          {
            "contract": "SliceCore",
            "label": "_maximumTransferBatch",
            "type": "t_uint16",
            "src": "contracts/sliceCore_v0.sol:30"
          },
          {
            "contract": "SliceCore",
            "label": "_basePath",
            "type": "t_string_storage",
            "src": "contracts/sliceCore_v0.sol:31"
          },
          {
            "contract": "SliceCore",
            "label": "_totalSupply",
            "type": "t_mapping(t_uint256,t_uint256)",
            "src": "contracts/sliceCore_v0.sol:32"
          },
          {
            "contract": "SliceCore",
            "label": "_slicers",
            "type": "t_mapping(t_uint256,t_address)",
            "src": "contracts/sliceCore_v0.sol:33"
          },
          {
            "contract": "SliceCore",
            "label": "_categoryIndex",
            "type": "t_struct(Counter)3129_storage",
            "src": "contracts/sliceCore_v0.sol:34"
          },
          {
            "contract": "SliceCore",
            "label": "_categoryAddresses",
            "type": "t_mapping(t_uint32,t_address)",
            "src": "contracts/sliceCore_v0.sol:35"
          }
        ],
        "types": {
          "t_uint16": {
            "label": "uint16"
          },
          "t_string_storage": {
            "label": "string"
          },
          "t_mapping(t_uint256,t_uint256)": {
            "label": "mapping(uint256 => uint256)"
          },
          "t_uint256": {
            "label": "uint256"
          },
          "t_mapping(t_uint256,t_address)": {
            "label": "mapping(uint256 => address)"
          },
          "t_address": {
            "label": "address"
          },
          "t_struct(Counter)3129_storage": {
            "label": "struct CountersUpgradeable.Counter",
            "members": [
              {
                "label": "_value",
                "type": "t_uint256"
              }
            ]
          },
          "t_mapping(t_uint32,t_address)": {
            "label": "mapping(uint32 => address)"
          },
          "t_uint32": {
            "label": "uint32"
          },
          "t_array(t_uint256)49_storage": {
            "label": "uint256[49]"
          },
          "t_bool": {
            "label": "bool"
          },
          "t_array(t_uint256)50_storage": {
            "label": "uint256[50]"
          },
          "t_mapping(t_uint256,t_mapping(t_address,t_uint256))": {
            "label": "mapping(uint256 => mapping(address => uint256))"
          },
          "t_mapping(t_address,t_uint256)": {
            "label": "mapping(address => uint256)"
          },
          "t_mapping(t_address,t_mapping(t_address,t_bool))": {
            "label": "mapping(address => mapping(address => bool))"
          },
          "t_mapping(t_address,t_bool)": {
            "label": "mapping(address => bool)"
          },
          "t_array(t_uint256)47_storage": {
            "label": "uint256[47]"
          }
        }
      }
    },
    "d7bb031f628e4381aa66cf5f098e851957dc1850f90dfe48f416c4ab01cb0bcb": {
      "address": "0x5Cef0380cE0aD3DAEefef8bDb85dBDeD7965adf9",
      "txHash": "0xa7b84462c7d589b47574aa2e9fb61dc2f1311d8fbcd30dc520a53e2cea1a21f1",
      "layout": {
        "storage": [
          {
            "contract": "Initializable",
            "label": "_initialized",
            "type": "t_bool",
            "src": "@openzeppelin/contracts-upgradeable/proxy/utils/Initializable.sol:21"
          },
          {
            "contract": "Initializable",
            "label": "_initializing",
            "type": "t_bool",
            "src": "@openzeppelin/contracts-upgradeable/proxy/utils/Initializable.sol:26"
          },
          {
            "contract": "ContextUpgradeable",
            "label": "__gap",
            "type": "t_array(t_uint256)50_storage",
            "src": "@openzeppelin/contracts-upgradeable/utils/ContextUpgradeable.sol:30"
          },
          {
            "contract": "ERC20Upgradeable",
            "label": "_balances",
            "type": "t_mapping(t_address,t_uint256)",
            "src": "@openzeppelin/contracts-upgradeable/token/ERC20/ERC20Upgradeable.sol:36"
          },
          {
            "contract": "ERC20Upgradeable",
            "label": "_allowances",
            "type": "t_mapping(t_address,t_mapping(t_address,t_uint256))",
            "src": "@openzeppelin/contracts-upgradeable/token/ERC20/ERC20Upgradeable.sol:38"
          },
          {
            "contract": "ERC20Upgradeable",
            "label": "_totalSupply",
            "type": "t_uint256",
            "src": "@openzeppelin/contracts-upgradeable/token/ERC20/ERC20Upgradeable.sol:40"
          },
          {
            "contract": "ERC20Upgradeable",
            "label": "_name",
            "type": "t_string_storage",
            "src": "@openzeppelin/contracts-upgradeable/token/ERC20/ERC20Upgradeable.sol:42"
          },
          {
            "contract": "ERC20Upgradeable",
            "label": "_symbol",
            "type": "t_string_storage",
            "src": "@openzeppelin/contracts-upgradeable/token/ERC20/ERC20Upgradeable.sol:43"
          },
          {
            "contract": "ERC20Upgradeable",
            "label": "__gap",
            "type": "t_array(t_uint256)45_storage",
            "src": "@openzeppelin/contracts-upgradeable/token/ERC20/ERC20Upgradeable.sol:361"
          },
          {
            "contract": "ERC1967UpgradeUpgradeable",
            "label": "__gap",
            "type": "t_array(t_uint256)50_storage",
            "src": "@openzeppelin/contracts-upgradeable/proxy/ERC1967/ERC1967UpgradeUpgradeable.sol:214"
          },
          {
            "contract": "UUPSUpgradeable",
            "label": "__gap",
            "type": "t_array(t_uint256)50_storage",
            "src": "@openzeppelin/contracts-upgradeable/proxy/utils/UUPSUpgradeable.sol:64"
          },
          {
            "contract": "OwnableSlice",
            "label": "_slice",
            "type": "t_address",
            "src": "contracts/utils/ownableSlice.sol:8"
          },
          {
            "contract": "OwnableSlice",
            "label": "_owner",
            "type": "t_address",
            "src": "contracts/utils/ownableSlice.sol:9"
          },
          {
            "contract": "OwnableSlice",
            "label": "__gap",
            "type": "t_array(t_uint256)49_storage",
            "src": "contracts/utils/ownableSlice.sol:58"
          },
          {
            "contract": "SLC",
            "label": "_sliceCoreAddress",
            "type": "t_address",
            "src": "contracts/slc_v0.sol:24"
          },
          {
            "contract": "SLC",
            "label": "_servicePrices",
            "type": "t_mapping(t_uint32,t_uint256)",
            "src": "contracts/slc_v0.sol:26"
          }
        ],
        "types": {
          "t_address": {
            "label": "address"
          },
          "t_mapping(t_uint32,t_uint256)": {
            "label": "mapping(uint32 => uint256)"
          },
          "t_uint32": {
            "label": "uint32"
          },
          "t_uint256": {
            "label": "uint256"
          },
          "t_array(t_uint256)49_storage": {
            "label": "uint256[49]"
          },
          "t_array(t_uint256)50_storage": {
            "label": "uint256[50]"
          },
          "t_mapping(t_address,t_uint256)": {
            "label": "mapping(address => uint256)"
          },
          "t_mapping(t_address,t_mapping(t_address,t_uint256))": {
            "label": "mapping(address => mapping(address => uint256))"
          },
          "t_string_storage": {
            "label": "string"
          },
          "t_array(t_uint256)45_storage": {
            "label": "uint256[45]"
          },
          "t_bool": {
            "label": "bool"
          }
        }
      }
    },
    "a0cd5ad40b0d41f253896cabda06735d90a590eb83c05886134f90874b926a4c": {
      "address": "0x115978100953D0Aa6f2f8865d11Dc5888f728370",
      "txHash": "0x144eead1ec289c639a29cd8642f4605562f4404977ec90fcff4fda444dfca685",
      "layout": {
        "storage": [
          {
            "contract": "Initializable",
            "label": "_initialized",
            "type": "t_bool",
            "src": "@openzeppelin/contracts-upgradeable/proxy/utils/Initializable.sol:21"
          },
          {
            "contract": "Initializable",
            "label": "_initializing",
            "type": "t_bool",
            "src": "@openzeppelin/contracts-upgradeable/proxy/utils/Initializable.sol:26"
          },
          {
            "contract": "ERC1967UpgradeUpgradeable",
            "label": "__gap",
            "type": "t_array(t_uint256)50_storage",
            "src": "@openzeppelin/contracts-upgradeable/proxy/ERC1967/ERC1967UpgradeUpgradeable.sol:214"
          },
          {
            "contract": "UUPSUpgradeable",
            "label": "__gap",
            "type": "t_array(t_uint256)50_storage",
            "src": "@openzeppelin/contracts-upgradeable/proxy/utils/UUPSUpgradeable.sol:64"
          },
          {
            "contract": "ContextUpgradeable",
            "label": "__gap",
            "type": "t_array(t_uint256)50_storage",
            "src": "@openzeppelin/contracts-upgradeable/utils/ContextUpgradeable.sol:30"
          },
          {
            "contract": "OwnableUpgradeable",
            "label": "_owner",
            "type": "t_address",
            "src": "@openzeppelin/contracts-upgradeable/access/OwnableUpgradeable.sol:21"
          },
          {
            "contract": "OwnableUpgradeable",
            "label": "__gap",
            "type": "t_array(t_uint256)49_storage",
            "src": "@openzeppelin/contracts-upgradeable/access/OwnableUpgradeable.sol:77"
          },
          {
            "contract": "PausableUpgradeable",
            "label": "_paused",
            "type": "t_bool",
            "src": "@openzeppelin/contracts-upgradeable/security/PausableUpgradeable.sol:28"
          },
          {
            "contract": "PausableUpgradeable",
            "label": "__gap",
            "type": "t_array(t_uint256)49_storage",
            "src": "@openzeppelin/contracts-upgradeable/security/PausableUpgradeable.sol:96"
          },
          {
            "contract": "ReentrancyGuardUpgradeable",
            "label": "_status",
            "type": "t_uint256",
            "src": "@openzeppelin/contracts-upgradeable/security/ReentrancyGuardUpgradeable.sol:37"
          },
          {
            "contract": "ReentrancyGuardUpgradeable",
            "label": "__gap",
            "type": "t_array(t_uint256)49_storage",
            "src": "@openzeppelin/contracts-upgradeable/security/ReentrancyGuardUpgradeable.sol:67"
          },
          {
            "contract": "Slice",
            "label": "upgradeableBeacon",
            "type": "t_contract(UpgradeableBeacon)3987",
            "src": "contracts/slice_v0.sol:49"
          },
          {
            "contract": "Slice",
            "label": "_SLCAddress",
            "type": "t_address",
            "src": "contracts/slice_v0.sol:51"
          },
          {
            "contract": "Slice",
            "label": "_sliceCoreAddress",
            "type": "t_address",
            "src": "contracts/slice_v0.sol:52"
          },
          {
            "contract": "Slice",
            "label": "priceFeed",
            "type": "t_contract(AggregatorV3Interface)45",
            "src": "contracts/slice_v0.sol:53"
          },
          {
            "contract": "Slice",
            "label": "_tokenIds",
            "type": "t_struct(Counter)3129_storage",
            "src": "contracts/slice_v0.sol:54"
          },
          {
            "contract": "Slice",
            "label": "_maximumSliceBatch",
            "type": "t_uint16",
            "src": "contracts/slice_v0.sol:55"
          },
          {
            "contract": "Slice",
            "label": "_maximumReleaseBatch",
            "type": "t_uint16",
            "src": "contracts/slice_v0.sol:56"
          }
        ],
        "types": {
          "t_contract(UpgradeableBeacon)3987": {
            "label": "contract UpgradeableBeacon"
          },
          "t_address": {
            "label": "address"
          },
          "t_contract(AggregatorV3Interface)45": {
            "label": "contract AggregatorV3Interface"
          },
          "t_struct(Counter)3129_storage": {
            "label": "struct CountersUpgradeable.Counter",
            "members": [
              {
                "label": "_value",
                "type": "t_uint256"
              }
            ]
          },
          "t_uint256": {
            "label": "uint256"
          },
          "t_uint16": {
            "label": "uint16"
          },
          "t_array(t_uint256)49_storage": {
            "label": "uint256[49]"
          },
          "t_bool": {
            "label": "bool"
          },
          "t_array(t_uint256)50_storage": {
            "label": "uint256[50]"
          }
        }
      }
    },
    "f30e40de3c5b5560e88b394c83b85453fd66e57528f387c3a4d321fac1cac1e7": {
      "address": "0xa4f6216c18102390B058Fe86EF652D39D193dD41",
      "txHash": "0x6df0a7add6316244c5eca8d80ac29a7b81a83b0384bab784dd5bb52eb3d1e6b8",
      "layout": {
        "storage": [
          {
            "contract": "Initializable",
            "label": "_initialized",
            "type": "t_bool",
            "src": "@openzeppelin/contracts-upgradeable/proxy/utils/Initializable.sol:21"
          },
          {
            "contract": "Initializable",
            "label": "_initializing",
            "type": "t_bool",
            "src": "@openzeppelin/contracts-upgradeable/proxy/utils/Initializable.sol:26"
          },
          {
            "contract": "ERC1967UpgradeUpgradeable",
            "label": "__gap",
            "type": "t_array(t_uint256)50_storage",
            "src": "@openzeppelin/contracts-upgradeable/proxy/ERC1967/ERC1967UpgradeUpgradeable.sol:214"
          },
          {
            "contract": "UUPSUpgradeable",
            "label": "__gap",
            "type": "t_array(t_uint256)50_storage",
            "src": "@openzeppelin/contracts-upgradeable/proxy/utils/UUPSUpgradeable.sol:80"
          },
          {
            "contract": "ContextUpgradeable",
            "label": "__gap",
            "type": "t_array(t_uint256)50_storage",
            "src": "@openzeppelin/contracts-upgradeable/utils/ContextUpgradeable.sol:30"
          },
          {
            "contract": "OwnableUpgradeable",
            "label": "_owner",
            "type": "t_address",
            "src": "@openzeppelin/contracts-upgradeable/access/OwnableUpgradeable.sol:21"
          },
          {
            "contract": "OwnableUpgradeable",
            "label": "__gap",
            "type": "t_array(t_uint256)49_storage",
            "src": "@openzeppelin/contracts-upgradeable/access/OwnableUpgradeable.sol:77"
          },
          {
            "contract": "PausableUpgradeable",
            "label": "_paused",
            "type": "t_bool",
            "src": "@openzeppelin/contracts-upgradeable/security/PausableUpgradeable.sol:28"
          },
          {
            "contract": "PausableUpgradeable",
            "label": "__gap",
            "type": "t_array(t_uint256)49_storage",
            "src": "@openzeppelin/contracts-upgradeable/security/PausableUpgradeable.sol:96"
          },
          {
            "contract": "ReentrancyGuardUpgradeable",
            "label": "_status",
            "type": "t_uint256",
            "src": "@openzeppelin/contracts-upgradeable/security/ReentrancyGuardUpgradeable.sol:37"
          },
          {
            "contract": "ReentrancyGuardUpgradeable",
            "label": "__gap",
            "type": "t_array(t_uint256)49_storage",
            "src": "@openzeppelin/contracts-upgradeable/security/ReentrancyGuardUpgradeable.sol:67"
          },
          {
            "contract": "Slice",
            "label": "upgradeableBeacon",
            "type": "t_contract(UpgradeableBeacon)4021",
            "src": "contracts/slice_v0.sol:49"
          },
          {
            "contract": "Slice",
            "label": "_SLCAddress",
            "type": "t_address",
            "src": "contracts/slice_v0.sol:51"
          },
          {
            "contract": "Slice",
            "label": "_sliceCoreAddress",
            "type": "t_address",
            "src": "contracts/slice_v0.sol:52"
          },
          {
            "contract": "Slice",
            "label": "priceFeed",
            "type": "t_contract(AggregatorV3Interface)45",
            "src": "contracts/slice_v0.sol:53"
          },
          {
            "contract": "Slice",
            "label": "_tokenIds",
            "type": "t_struct(Counter)3163_storage",
            "src": "contracts/slice_v0.sol:54"
          },
          {
            "contract": "Slice",
            "label": "_maximumSliceBatch",
            "type": "t_uint16",
            "src": "contracts/slice_v0.sol:55"
          },
          {
            "contract": "Slice",
            "label": "_maximumReleaseBatch",
            "type": "t_uint16",
            "src": "contracts/slice_v0.sol:56"
          }
        ],
        "types": {
          "t_contract(UpgradeableBeacon)4021": {
            "label": "contract UpgradeableBeacon"
          },
          "t_address": {
            "label": "address"
          },
          "t_contract(AggregatorV3Interface)45": {
            "label": "contract AggregatorV3Interface"
          },
          "t_struct(Counter)3163_storage": {
            "label": "struct CountersUpgradeable.Counter",
            "members": [
              {
                "label": "_value",
                "type": "t_uint256"
              }
            ]
          },
          "t_uint256": {
            "label": "uint256"
          },
          "t_uint16": {
            "label": "uint16"
          },
          "t_array(t_uint256)49_storage": {
            "label": "uint256[49]"
          },
          "t_bool": {
            "label": "bool"
          },
          "t_array(t_uint256)50_storage": {
            "label": "uint256[50]"
          }
        }
      }
    }
  }
}
